modelhub/__init__.py
modelhub/client.py
modelhub/decorators.py
modelhub/models.py
modelhub/pipelines.py
modelhub/utils.py
modelhub/utils/__init__.py
modelhub/utils/logger.py
modelhub/utils/response.py
recipe_project/__init__.py
recipe_project/main.py
recipe_project/steps/__init__.py
recipe_project/steps/evaluate.py
recipe_project/steps/preprocess.py
recipe_project/steps/train.py
tests/__init__.py
modelhub_sdk-0.1.21.dist-info/METADATA
modelhub_sdk-0.1.21.dist-info/WHEEL
modelhub_sdk-0.1.21.dist-info/top_level.txt
modelhub_sdk-0.1.21.dist-info/RECORD
