Metadata-Version: 2.1
Name: modelhub-sdk
Version: 0.1.21
Summary: SDK for ModelHub to create and manage machine learning pipelines
Home-page: https://github.com/yourusername/modelhub-sdk
Author: Jagveer Singh
Author-email: jagveer@autonomize.ai
Classifier: Programming Language :: Python :: 3
Classifier: License :: OSI Approved :: MIT License
Classifier: Operating System :: OS Independent
Requires-Python: >=3.9
Requires-Dist: pandas
Requires-Dist: pyyaml
Requires-Dist: jinja2
Requires-Dist: kubernetes
Requires-Dist: requests
Requires-Dist: aiohttp
Requires-Dist: mlflow
Requires-Dist: azure-storage-blob
Requires-Dist: azure-identity
Requires-Dist: graphviz
Requires-Dist: IPython
Requires-Dist: pydantic
Requires-Dist: networkx
